uwsgicache.py
django_uwsgi_cache-1.1.0.dist-info/licenses/LICENSE
django_uwsgi_cache-1.1.0.dist-info/METADATA
django_uwsgi_cache-1.1.0.dist-info/WHEEL
django_uwsgi_cache-1.1.0.dist-info/top_level.txt
django_uwsgi_cache-1.1.0.dist-info/RECORD
