Metadata-Version: 2.4
Name: django-uwsgi-cache
Version: 1.1.0
Summary: uWSGI Django cache backend.
Author-email: Ionel Cristian Mărieș <contact@ionelmc.ro>
License-Expression: BSD-2-Clause
Project-URL: Sources, https://github.com/ionelmc/django-uwsgi-cache
Project-URL: Documentation, https://django-uwsgi-cache.readthedocs.io/
Project-URL: Changelog, https://django-uwsgi-cache.readthedocs.io/en/latest/changelog.html
Project-URL: Issue Tracker, https://github.com/ionelmc/django-uwsgi-cache/issues
Classifier: Development Status :: 5 - Production/Stable
Classifier: Intended Audience :: Developers
Classifier: Operating System :: Unix
Classifier: Operating System :: POSIX
Classifier: Operating System :: Microsoft :: Windows
Classifier: Programming Language :: Python
Classifier: Programming Language :: Python :: 3
Classifier: Programming Language :: Python :: 3 :: Only
Classifier: Programming Language :: Python :: 3.9
Classifier: Programming Language :: Python :: 3.10
Classifier: Programming Language :: Python :: 3.11
Classifier: Programming Language :: Python :: 3.12
Classifier: Programming Language :: Python :: 3.13
Classifier: Programming Language :: Python :: Implementation :: CPython
Classifier: Topic :: Utilities
Requires-Python: >=3.9
License-File: LICENSE
Requires-Dist: django>=4.2
Dynamic: description
Dynamic: description-content-type
Dynamic: license-file
